quentinrosinski_picsou/__init__.py
quentinrosinski_picsou/picsou.py
quentinrosinski_picsou-0.2.0.dist-info/METADATA
quentinrosinski_picsou-0.2.0.dist-info/WHEEL
quentinrosinski_picsou-0.2.0.dist-info/RECORD
