Metadata-Version: 2.1
Name: quentinrosinski-picsou
Version: 0.2.0
Summary: 
Author: Quentin Rosinski
Author-email: quentin.rosinski@icloud.com
Requires-Python: >=3.12,<4.0
Classifier: Programming Language :: Python :: 3
Classifier: Programming Language :: Python :: 3.12
Requires-Dist: pillow (>=10.2.0,<11.0.0)
